cfabric/__init__.py
cfabric/describe.py
cfabric/py.typed
cfabric/results.py
cfabric/types.py
cfabric/core/__init__.py
cfabric/core/api.py
cfabric/core/config.py
cfabric/core/fabric.py
cfabric/downloader/__init__.py
cfabric/downloader/download.py
cfabric/downloader/paths.py
cfabric/downloader/registry.py
cfabric/features/__init__.py
cfabric/features/computed.py
cfabric/features/edge.py
cfabric/features/node.py
cfabric/features/warp/__init__.py
cfabric/features/warp/oslots.py
cfabric/features/warp/otype.py
cfabric/io/__init__.py
cfabric/io/compiler.py
cfabric/io/loader.py
cfabric/navigation/__init__.py
cfabric/navigation/locality.py
cfabric/navigation/nodes.py
cfabric/navigation/text.py
cfabric/precompute/__init__.py
cfabric/precompute/prepare.py
cfabric/search/__init__.py
cfabric/search/graph.py
cfabric/search/relations.py
cfabric/search/search.py
cfabric/search/searchexe.py
cfabric/search/semantics.py
cfabric/search/spin.py
cfabric/search/stitch.py
cfabric/search/syntax.py
cfabric/storage/__init__.py
cfabric/storage/csr.py
cfabric/storage/mmap_manager.py
cfabric/storage/string_pool.py
cfabric/utils/__init__.py
cfabric/utils/attrs.py
cfabric/utils/cli.py
cfabric/utils/files.py
cfabric/utils/helpers.py
cfabric/utils/logging.py
context_fabric-0.5.6.dist-info/METADATA
context_fabric-0.5.6.dist-info/WHEEL
context_fabric-0.5.6.dist-info/top_level.txt
context_fabric-0.5.6.dist-info/RECORD
