Metadata-Version: 2.4
Name: context-fabric
Version: 0.5.6
Summary: Graph-based corpus engine for annotated text with efficient traversal and search
Author: Cody Kingham, Dirk Roorda
License: MIT
Project-URL: Homepage, https://context-fabric.ai
Project-URL: Documentation, https://context-fabric.ai/docs
Project-URL: Repository, https://github.com/Context-Fabric/context-fabric
Project-URL: Issues, https://github.com/Context-Fabric/context-fabric/issues
Keywords: text,linguistics,annotation,corpus,graph
Classifier: Development Status :: 3 - Alpha
Classifier: Intended Audience :: Developers
Classifier: Intended Audience :: Science/Research
Classifier: License :: OSI Approved :: MIT License
Classifier: Operating System :: OS Independent
Classifier: Programming Language :: Python :: 3
Classifier: Programming Language :: Python :: 3.13
Classifier: Topic :: Text Processing :: Linguistic
Classifier: Topic :: Scientific/Engineering :: Information Analysis
Requires-Python: >=3.13
Requires-Dist: numpy>=1.26
Requires-Dist: pyyaml>=5.3
Provides-Extra: dev
Requires-Dist: pytest>=7.0; extra == "dev"
Requires-Dist: pytest-cov; extra == "dev"
Requires-Dist: ruff; extra == "dev"
Provides-Extra: mcp
Requires-Dist: cfabric-mcp>=0.1.0; extra == "mcp"
Provides-Extra: benchmarks
Requires-Dist: cfabric-benchmarks>=0.1.0; extra == "benchmarks"
Provides-Extra: docs
Requires-Dist: griffe>=1.0; extra == "docs"
Requires-Dist: griffe-typingdoc>=0.2; extra == "docs"
